{
  "start": "시작",
  "quit": "게임을 종료 하시겠습니까?",
  "check_network": "네트워크 연결을\\n확인해 주세요.",
  "new_update": "새로운 업데이트가 있습니다.\\n업데이트를 해주세요!",
  "sold_out": "구매완료",
  "purchase_cancel": "구매가 취소 되었습니다.",
  "next_time": "좋아 다음에",
  "nope": "안해",
  "yes": "예",
  "no": "아니오",
  "ok": "확인",
  "cancle": "취소",
  "resume": "게임으로 돌아가기",
  "retry": "다시하기",
  "exit": "끝내기",
  "want_purchase": "구매 하시겠습니까?",
  "no_ads": "광고 없음",
  "new_game": "새로운 게임",
  "tap_to_play": "터치하여 시작",
  "like_us": "좋아요!!",
  "rank": "순위",
  "shop": "상점",
  "daily_bonus": "일일 보너스",
  "watching_ad": "짧은 광고 시청 후\\n보너스 아이템을 받으시겠어요?",
  "information": "안내",
  "bouns": "보너스",
  "notice": "알림",
  "complete": "완료",
  "completes": "{0} 완성되었습니다.",
  "setting": "설정",
  "reward_Item": "보상 획득",
  "how_to_play": "게임 방법",
  "next": "다음",
  "connect_network": "결제를 하시려면\\n네트워크에 연결하세요.",
  "no_ads_offline": "오프라인 상태에서는\\n리워드 광고를 볼 수 없습니다.",
  "daily_mission": "일일 미션",
  "collect_reward": "보상받기",
  "congratulations": "축하합니다!",
  "mission_clear": "미션 클리어",
  "language": "한국어",
  "loading": "Loading...",
  "time_hour_local": "시간",
  "time_min_local": "분",
  "time_sec_local": "초",
  "time_day_local": "일",
  "st_local": "1등",
  "nd_local": "2등",
  "rd_local": "3등",
  "th_local": "{0}등",
  "open_reward": "보상 받기",
  "not_exist": "미습득",
  "leaderboard": "랭킹",
  "rank_today": "일간",
  "rank_weekly": "주간",
  "rank_total": "전체",
  "rank_points": "점",
  "rank_me": "ME",
  "invite_friends": "친구초대",
  "game_start": "게임시작",
  "language_ko_kr": "한국어",
  "language_en_us": "ENGLISH",
  "language_ja_jp": "日本語",
  "language_es_es": "Español",
  "language_de_de": "Deutsch",
  "language_fr_fr": "français",
  "language_pt_br": "Português",
  "language_zh_cn": "中文(簡体)",
  "language_zh_tw": "中文(繁體)",
  "language_ru_ru": "Русский",
  "language_it_it": "Italiano",
  "language_id_id": "Indonesia",
  "setting_ko_kr": "설정",
  "setting_en_us": "SETTING",
  "setting_ja_jp": "設定",
  "setting_es_es": "CONFIGURACIÓN",
  "setting_de_de": "EINSTELLUNG",
  "setting_fr_fr": "PARAMÈTRES",
  "setting_pt_br": "CONFIGURAÇÕES",
  "setting_zh_cn": "设置",
  "setting_zh_tw": "設置",
  "setting_ru_ru": "НАСТРОЙКИ",
  "setting_it_it": "IMPOSTAZIONI",
  "setting_id_id": "PENGATURAN",
  "invite_message": "{0}님과 함께 {1}을(를) 즐겨보세요!",
  "exit_language": "Language setting will be\\nchanged after restart.",
  "ok_language": "OK",
  "exit_title": "EXIT",
  "error_nofill": "광고가 모두 소진되어 더 재생할 수 없습니다.\\n({0})",
  "error_unsupported": "현재 환경에서는 광고 재생이 불가능합니다.\\n({0})",
  "total_rank": "전체랭킹",
  "friend_rank": "친구랭킹",
  "friend_share": "자랑하기",
  "rank_init": "{0} 초기화",
  "rest": "남음",
  "share_msg": "짜잔~! {0}점 달성!!\\n날 이기고 싶으면 지금 바로 도전 gogogo!",
  "share_button": "게임 바로가기",
  "rank_format": "상위 {0}%",
  "talk_room_start": "#{0} 톡방랭킹을 시작합니다.",
  "reset_talk_room_rank": "72시간 동안 플레이 없는 경우 초기화",
  "invite_snack": "나랑 같이 스낵게임할래?",
  "app_name": "솔리테어 쿠킹 타워",
  "btn_play": "플레이",
  "hint": "힌트",
  "undo": "되돌리기",
  "shuffle": "패 섞기",
  "mission": "미션",
  "onecard": "한 장씩",
  "threecard": "세 장씩",
  "back": "돌아가기",
  "newgame": "새로하기",
  "puase": "일시정지",
  "record": "통계",
  "stickyhands": "더 많은 게임",
  "auto": "자동완성",
  "autocomplete": "자동완성을\\n진행합니다.",
  "rate": "승률",
  "winningstreak": "연승",
  "totalgamecount": "전체 게임수",
  "wingamecount": "이긴 게임수",
  "bestcoincount": "최고 획득 코인",
  "totalgametime": "전체 게임 시간",
  "bestwintime": "승리 최단 시간",
  "avgwintime": "승리 평균 시간",
  "left": "왼쪽",
  "right": "오른쪽",
  "save": "게임 데이터 관리",
  "fbloginfaile": "Facebook Login 실패.\n재시도 하시겠습니까?",
  "datasync": "데이터 동기화",
  "saveserver": "서버에 저장하기",
  "loadserver": "기기에 내려받기",
  "inuse": "사용중",
  "use": "사용",
  "card": "카드",
  "cardcollection": "카드 콜렉션",
  "item": "아이템",
  "add": "추가",
  "enough_coin": "코인이 부족합니다.",
  "add_new_menu": "신메뉴가 추가 되었습니다.\n\n벌써 소문을 듣고 손님들이 몰리고 있어요!",
  "abilitycoin": "정산시",
  "timebonus": "시간 보너스 +",
  "streakbonus": "{0} 연승 보너스({1}%) +",
  "drawbonus": "세 장씩 넘기기 보너스({0}%) +",
  "deckbonus": "카드 덱 보너스 +",
  "combobonus": "콤보 보너스 +",
  "add_menu_check": "메뉴를 구매 하시겠습니까?",
  "can_not_add_menu": "아직 메뉴를 추가할 수 없습니다.",
  "streakbonus0": "연승 보너스 +",
  "addhint": "{0}힌트 구매가\n완료 되었습니다",
  "addundo": "{0}되돌리기 구매가\n완료 되었습니다",
  "addshuffle": "{0}패 섞기 구매가\n완료 되었습니다",
  "addspecial": "{0}힌트, {1}되돌리기\n{2}패 섞기\n구매가 완료 되었습니다.",
  "noadspurchase": "광고제거 구매가\n완료 되었습니다.",
  "noadsrestore": "광고제거 구매복원이\n완료 되었습니다.",
  "cardpurchase": "{0}별을 사용하여\n[{1}]카드를\n구매 하시겠습니까?",
  "starnotenough": "{0}별이\n부족합니다.",
  "checkinternet": "네트워크 연결을\n확인해 주세요.",
  "choosecard": "카드를 선택하고\n특별한 선물을 받으세요!",
  "dailymission": "데일리 미션",
  "achievements": "업적",
  "missionrefresh": "매일 미션이 갱신됩니다.",
  "dmpoint": "{0} 코인 획득",
  "dmcontinuewin": "누적승리 {0}회",
  "dmtimewin": "{0}' {1}″ 안에 승리 3회 하기",
  "dmwinningstreak": "{0}연승 하기",
  "winsinarow": "{0} 연승",
  "yourreward": "당신의 보상은 : ",
  "winsinarow_sub": "연승",
  "newgamebtn": "새 게임",
  "bestwinningstreak": "최고 연승",
  "datasynctext": "Facebook에 연결 한 경우\n다양한 장치에서 플레이 할 수 있습니다.",
  "serverdata": "서버 데이터",
  "devicedata": "기기 데이터",
  "notserverdata": "저장된 데이터가 없습니다",
  "fail_connection": "서버 연결에 실패 하였습니다",
  "local_to_server": "기기의 데이터를 서버에 저장합니다.\n기존 서버 데이터가\n기기 데이터로 갱신됩니다.\n\n계속 진행하시겠습니까?",
  "server_to_local": "서버 데이터를 기기 데이터로 갱신됩니다.\n계속 진행하시겠습니까?\n\n앱이 새로 시작됩니다. ",
  "server_in_sync": "서버와 기기의 데이터가\n동기화 되었습니다.",
  "game_exit_msg": "게임을 종료하시겠습니까?",
  "initinfos": "{0}를 하면\n{1}연승 기록이 초기화 됩니다.\n\n{2}를 하시겠습니까?",
  "initinfo": "{0}를 하면\n연승기록이 초기화 됩니다.\n\n{1}를 하시겠습니까?",
  "goodjob": "GOOD JOB!",
  "gamemodechange": "{0} 카드로 새게임이 시작됩니다.\n연승기록은 유지됩니다. ",
  "review": "재밌게 즐기신 만큼 리뷰를 남겨주시면\n저희 개발자들에게 큰 힘이 됩니다.\n\n남겨.. 주실꺼죠? *^^*",
  "reviewok": "까짓꺼.. 남겨 주겠어!",
  "reviewlater": "좋아 다음에..",
  "playgraph": "주간 플레이 그래프",
  "adscat": "짧은 광고 시청 후\n보너스 아이템을 받으시겠어요?",
  "norestore": "구매 복원할 항목이 없습니다.",
  "removeads": "광고 제거",
  "purchasecomplete": "구매 완료",
  "will_retry": "재시도 합니다.",
  "iab_fail_info": "구매가 실패하였습니다.\n\n앱을 재실행 후에도 \n아이템 지급이 되지 않는다면, \ndev@stickyhands.kr 문의 바랍니다.",
  "adsbonusreward": "보상 아이템",
  "comingsoon": "Coming soon",
  "menu_preparing": "메뉴 준비중",
  "menu_chef": "Yes! Chef!",
  "localnoti": "게임 내 알림",
  "push_reward_store": "[{0}] 의 별을 획득 하세요!",
  "specialpackage": "스패셜 패키지",
  "givenoads": "아이템을 구매하시면 팝업 광고가 제거 됩니다.",
  "star": "별",
  "nohintitem": "힌트 아이템이 없습니다.\n구매 하시겠습니까?",
  "noundoitem": "되돌리기 아이템이 없습니다.\n구매 하시겠습니까?",
  "noshuffleitem": "패 섞기 아이템이 없습니다.\n구매 하시겠습니까?",
  "dmgetstar": "{0}별 획득",
  "dmcomborun": "{0}콤보 카드 발동",
  "ealryresult": "RESULT",
  "newmenuadd": "새로운 메뉴 추가 완료!",
  "menu_add_complete": "새로운 메뉴가 완성 되었습니다.",
  "guest": "벌써 소문을 듣고 손님들이 몰리고 있어요!",
  "restaurant_clear": "{0} 클리어!",
  "min_coin": "{0}분 마다 {1}별 생성\n자주 방문해서 별을 획득하세요.",
  "restaurant_open": "[{0}] 오픈!",
  "restaurant_open_msg": "새로운 레스토랑을 완성하세요!",
  "nomorehint": "힌트를 사용할 수 없는 상태입니다.",
  "ageofsolitairecard": "에이지오브솔리테어를 설치하시면,\n카드를 받을 수 있습니다.\n\n다운 받으러 가시겠어요?",
  "reward": "보상",
  "restaurant_empty": "신사업 구상중…",
  "restaurant_empty_msg": "게임을 즐기면서 별을 모으세요.",
  "sharestatistics": "당신의 기록을 공유해보세요!",
  "installshareapp": "먼저 {0} 앱을 설치 후\n다시 시도 해 주세요.",
  "facebook": "페이스북",
  "twitter": "트위터",
  "instagram": "인스타그램",
  "login_fail": "로그인에 실패 하였습니다.",
  "platform_choice_info": "위 플랫폼에 연결 한 경우\n다양한 장치에서 플레이 할 수 있습니다.",
  "sign_facebook": "Sign in with Facebook",
  "sign_google": "Sign in with Google",
  "sign_gamecenter": "Sign in with GameCenter",
  "change_account": "계정전환",
  "dmads": "동영상광고 {0}회 시청",
  "dmgameplay": "게임플레이 {0}회",
  "dmmenuopen": "메뉴오픈 {0}회",
  "dmmenushare": "메뉴 공유 하기 {0}회",
  "dmtowershare": "타워 공유 하기 {0}회",
  "dmstatshare": "통계 공유 하기 {0}회",
  "dmshuffleuse": "셔플 아이템 {0}회 사용",
  "dmhintuse": "힌트 아이템 {0}회 사용",
  "dmundouse": "되돌리기 아이템 {0}회 사용",
  "addstar": "{0}별 구매가\n완료 되었습니다.",
  "adskippurchase": "광고스킵권 구매가\n완료 되었습니다.",
  "adskiprestore": "광고스킵권 복원이\n완료 되었습니다.",
  "seedetail": "자세히 보기",
  "videoskip": "동영상 광고 스킵",
  "limitedpackage": "앨리스 카드덱 패키지",
  "adsdouble": "짧은 동영상 광고 시청 후,\n코인을 두배로 받으시겠습니까?",
  "limited01purchase": "앨리스 카드덱 패키지\n구매가 완료 되었습니다.",
  "limited01restore": "앨리스 카드덱 패키지\n복원이 완료 되었습니다.",
  "videoskipbonus": "동영상 광고 스킵 +",
  "howto": "게임방법",
  "restore": "구매복원",
  "coin": "코인",
  "attendreward": "Daily Check",
  "attenddesc": "매일 매일 접속하고 특별한 상품을 받으세요!",
  "buyattend": "출석보상",
  "buyeffect": "구매효과",
  "discount10": "모든메뉴 10% 할인",
  "welcome": "어서오세요!",
  "menu": "메뉴 관리",
  "combo": "콤보",
  "playgamehelp0": "\n\n솔리테어 쿠킹타워는 솔리테어 게임을\n하면서 획득한 코인으로 다양한 메뉴를\n오픈하고 식당을 운영하는 게임입니다. \n\n자 먼저 제일 중요한 솔리테어\n게임 방법을 알려드릴께요.",
  "playgamehelp1": "카드들이 7줄로 나열되어 있는\n하단 부분이 타블로 입니다. \n타블로에 있는 카드들을 탭을 하거나\n드래그하여 다른 줄로 이동시키면서\nK부터 에이스까지 내림차순으로 카드를\n쌓을 수 있습니다. ",
  "playgamehelp2": "이때, 빨간색과 검은색 카드를 교차하여\n번갈아 쌓을 수 있으며, \n빈 줄에는 K만 이동할 수 있습니다. \n\n더 이상 타블로에 이동할 카드가 없으면\n웨이스트 부분을 탭하여\n새로운 카드를 볼 수 있습니다.",
  "playgamehelp3": "상단에 빈 곳은 파운데이션입니다.\n\n에이스부터 K까지 순차적으로\n파운데이션에 4벌의 카드덱을 모두\n쌓으면 게임을 클리어 하게 됩니다.",
  "playgamehelp4": "솔리테어 게임을 진행하면서 \n획득한 점수에 따라 \n식당의 메뉴를 오픈할 수 있으며,\n\n모든 메뉴를 오픈하면\n새로운 식당에 도전할 수 있습니다.",
  "playgamehelp5": "연속득점을 하게 되면 콤보 게이지가 쌓입니다.\n\n5콤보를 하면 제일 위에 있는 카드중\n하나의 카드에 콤보 효과가 발동됩니다.\n발동된 카드를 10초 안에 파운데이션으로\n옮기면 별을 획득할 수 있습니다.",
  "playgamehelp6": "카드 상점에서 별을 사용하여\n다양한 카드를 구매할 수 있습니다.\n\n카드마다 특별한 효과가 있습니다.",
  "playgamehelp7": "모든 튜토리얼을 마쳤습니다.\n\n이제 솔리테어를 즐기면서\n다양한 식당을 만들어 보세요!",
  "book": "도감",
  "store_1": "Minu's HOTDOG",
  "store_2": "Ahin's Taco",
  "store_3": "HO Express",
  "store_4": "Goon's Sushi",
  "store_5": "Tein's Pizza house",
  "store_6": "JJi's Cupcakes",
  "store_7": "Seol's Hot-Thai",
  "store_8": "Gung-nyeo's Korean Food",
  "store_9": "James' Din Tai Pung",
  "store_10": "Carlos' Bistro",
  "store_11": "Burgur Queen",
  "menu_11": "플레인 핫도그",
  "menu_12": "치즈 핫도그",
  "menu_13": "레리쉬 핫도그",
  "menu_14": "칠리&치즈 핫도그",
  "menu_15": "닭가슴살 번",
  "menu_21": "타코 샐러드",
  "menu_22": "치킨 타코",
  "menu_23": "카니타스 타코",
  "menu_24": "트리빠스 타코",
  "menu_25": "치뽀뜰레 새우 타코",
  "menu_31": "쵸우멘",
  "menu_32": "오렌지 치킨",
  "menu_33": "가지 & 두부",
  "menu_34": "허니 월넛 쉬림프",
  "menu_35": "베이징 비프",
  "menu_41": "계란 초밥",
  "menu_42": "연어알 초밥",
  "menu_43": "장어 초밥",
  "menu_44": "참치 대뱃살 초밥",
  "menu_45": "모듬 초밥",
  "menu_51": "마르게리타 피자",
  "menu_52": "콰트로 스타조니 피자",
  "menu_53": "버섯 피자",
  "menu_54": "루꼴라 피자",
  "menu_55": "포테이토 피자",
  "menu_61": "바나나 컵케이크",
  "menu_62": "초코 컵케이크",
  "menu_63": "베리베리 컵케이크",
  "menu_64": "당근 컵케이크",
  "menu_65": "레드벨벳 컵케이크",
  "menu_71": "모닝글로리 볶음",
  "menu_72": "팟타이",
  "menu_73": "쏨땀",
  "menu_74": "풋팟퐁커리",
  "menu_75": "똠양꿍",
  "menu_81": "김치전",
  "menu_82": "잡채",
  "menu_83": "닭강정",
  "menu_84": "비빔밥",
  "menu_85": "떡갈비",
  "menu_91": "새우완탕스프",
  "menu_92": "새우샤오마이",
  "menu_93": "야채쩡짜오",
  "menu_94": "고기따바오",
  "menu_95": "게살샤오롱바오",
  "menu_101": "타파스",
  "menu_102": "감바스",
  "menu_103": "가스파초",
  "menu_104": "토르티야",
  "menu_105": "빠에야",
  "menu_111": "버거 주니어",
  "menu_112": "치즈 버거",
  "menu_113": "슈프림 쉬림프 버거",
  "menu_114": "스파이시 치킨 버거",
  "menu_115": "스테이크더블치즈버거",
  "mdesc_11": "케찹 또는 머스터드와 함께 간편하게\n즐길 수 있는 클래식 핫도그",
  "mdesc_12": "저지방의 담백한 치즈 소스를 얹은\n부드러운 핫도그",
  "mdesc_13": "다진 오이에 새콤, 달콤한 맛의\n소스를 얹은 핫도그",
  "mdesc_14": "매콤하게 양념한 닭가슴살 위에 부드럽고\n담백한 모짜렐라 치즈를 얹은 프리미엄 핫도그",
  "mdesc_15": "고단백 저칼로리인 닭 가슴살만을 소스에\n약간 버무려 샌드 형식으로 만든 신개념의 번",
  "mdesc_21": "다진 소고기와 신선한 샐러드, 피코데가요,\n치즈, 샐러드 드레싱이 곁들어진\n상큼한 셀러드",
  "mdesc_22": "향긋하고 매콤한 닭 다리살 볶음이\n주 재료인 타코",
  "mdesc_23": "오렌지와 향신료로 삶은 후 바삭하게 구운\n돼지고기가 주 재료인 타코",
  "mdesc_24": "멕시코식으로 정성스레 만든\n소 곱창구이가 주 재료인 타코",
  "mdesc_25": "치뽀뜰레 고추로 양념한 새우, 버섯\n볶음이 주 재료인 타코",
  "mdesc_31": "계란으로 만든 면을 돼지고기와\n양배추 등과 함께 굴소스와 간장을\n메인으로 한 볶음 면요리",
  "mdesc_32": "닭고기를 튀긴 후, 달콤하면서\n살짝 매콤한 오렌지 소스를 끼얹은 요리",
  "mdesc_33": "가지와 두부를\n살짝 매콤하게 볶은 야채 요리",
  "mdesc_34": "새우튀김과 고소한 호두에 달콤한\n꿀소스를 버무린 환상조합의 요리",
  "mdesc_35": "부드러운 소고기를 튀긴 후 새콤달콤한\n탕수 소스를 얹은 최고의 요리",
  "mdesc_41": "달콤하고 부드러운 계란말이 초밥으로\n어린이들에게 인기만점. ",
  "mdesc_42": "맛있게 절인 연어 알로 만든 초밥으로 입에서 톡톡 터지는 육즙이 입을 즐겁게 한다.",
  "mdesc_43": "짭조롬한 양념과 탱글탱글한 장어 살의\n식감이 일품인 장어초밥으로 맥주와의 궁합이\n일품이다.",
  "mdesc_44": "참치의 최고 초밥 재료인 뱃살로 만든 스시로\n담백하고 고소한 맛이 일품인 초밥의 왕",
  "mdesc_45": "최고의 솜씨로 빚은 다양한 초밥 모듬 세트로\n신선한 바다를 맛볼 수 있는 기회.",
  "mdesc_51": "이탈리아 국기 색을 나타내는 모짜렐라,\n토마토, 바질을 넣어 만든 가장 대중적인 피자.",
  "mdesc_52": "피자 한판에 4가지 맛을 담은 피자로\n올리브, 버섯, 햄, 토마토 등으로 4계절을\n나타낸다. ",
  "mdesc_53": "버섯으로 토핑한 피자로 쫄깃한 식감으로\n많은 사랑을 받는다.",
  "mdesc_54": "이태리 요리에 많이 쓰는 루꼴라를 주\n토핑으로 한 피자로 상큼하고 건강한 피자이다.",
  "mdesc_55": "감자와 베이컨을 주 토핑으로 한 피자로\n식감이 좋고 Tein 요리사가 제일 좋아하는\n피자이다.",
  "mdesc_61": "간식으로 영양 만점! 향긋하고 달콤한 바나나\n컵케이크. 초코칩 넣어 주실꺼죠?",
  "mdesc_62": "기분이 나빴다가도 한입 베어물면 행복하게\n만들어 주는 달달한 초코 컵케이크.",
  "mdesc_63": "블루베리, 라즈베리, 딸기 등의 상큼한\n과일이 달콤한 케이크와 만나 나의 이성을\n잃게 만든다. ",
  "mdesc_64": "평소에 당근은 잘 안먹는데, \n당근 컵케이크는 왜이리 맛있는거지? \n셰프님이 마법을 부렸나봐!",
  "mdesc_65": "식욕을 유혹하는 화려한 비주얼과 \n너무나 고급진 맛!\n오늘 나를 위한 선물은 바로 너.",
  "mdesc_71": "물시금치(모닝글로리)를 굴소스와 \n태국 간장 등으로 맛있게 볶은 채소 요리로 \n짭쪼롬 한것이 식욕을 북돋아준다",
  "mdesc_72": "태국의 대표적인 쌀국수 볶음 요리로 \n식성에 따라 해산물이나 닭고기, 돼지고기 \n등을 다양한 야채와 함께 맛있게 볶은 요리",
  "mdesc_73": "그린파파야를 썰어서 만든 셀러드로 \n매콤하면서 감칠맛이 있어 자꾸 손이 가는 \n건강 샐러드이다",
  "mdesc_74": "게를 커리에 볶아낸 음식으로 쫄깃하고 담백한 게살과 부들운 코코넛 크림과 커리의 향, 그리고 아삭거리는 야채가 어우러져 꼭 먹어야 할 태국 요리",
  "mdesc_75": "세계 3대 스프로 유명한 태국의 똠양꿍은 매콤하면서도 새콤한 맛이 일품인 태국식 새우탕",
  "mdesc_81": "잘 익은 김치를 잘게 썰어 넣은 밀가루 반죽을 구워 만들어 낸 부침개 요리. 바삭한 김치전은 모든 주류에 어울리는 최고의 안주다. ",
  "mdesc_82": "당면을 다양한 채소와 고기를 넣고 볶아낸 요리로 한국의 잔치에 빠지지 않는 대표 음식이다. ",
  "mdesc_83": "튀긴 닭고기를 달고 매콤한 양념에 조려낸 요리. 물엿의 달콤함과 땅콩의 고소함이 양념치킨과는 또다른 환상적인 맛이다. ",
  "mdesc_84": "다양한 나물을 고추장에 비벼먹는 한국의 대표적인 요리. 스트레스 받을 때, 우걱우걱 먹으면 어느새 스트레스 안녕!",
  "mdesc_85": "잘게 다진 소고기 갈비살을 떡모양으로 만들어 구워 먹는 한국의 전통 고기 요리. 쫀득하고 고소한 소고기 맛에 남녀노소 모두 좋아하는 요리.",
  "mdesc_91": "오동통통한 새우완탕과 부드러운 두부와 폭신한 계란맛이 일품인 국물요리. 추운날 담백하고 깔끔한 국물맛이 일품이다. ",
  "mdesc_92": "칵테일 새우가 얹어져 있고 윗부분으로 속이 보이는 작은 만두. 한입 물었을 때 터져나오는 육즙이 정말 맜있다. ",
  "mdesc_93": "반달모양으로 주름을 잡아 만든 딤섬으로 야채의 아삭함과 돼지고기의 풍부한 육즙이 일품이다. ",
  "mdesc_94": "겉껍질이 두툼하고 푹신한 고기 왕만두로 한입 가득 씹는 맛이 너무 좋다. ",
  "mdesc_95": "작은 대나무 찜통에 쪄낸 중국식 만두. 숟가락에 얹어 먼저 육즙을 마신후 나머지를 먹어야 한다. 한번에 먹으면 뜨거운 육즙에 입을 데일 수 있다. ",
  "mdesc_101": "스페인 안달루시아 지역에서 유래한 전채요리로 바게뜨 빵위에 올리브와 소시지, 파프리카, 참치 등 다양한 재료를 얹어 가벼운 술안주로 인기가 있다.",
  "mdesc_102": "스페인의 새우요리로 주로 마늘과 함께 올리브유에 푹 빠뜨려 조리한 요리로 매우 간단하지만 한번 먹으면 자꾸만 생각나는 그맛이다.",
  "mdesc_103": "주로 토마토와 함께 여러가지 야채를 잘게 썰거나 \n갈아 마늘을 조금 넣어 섞어 시원하게 만드는 냉수프. \n아 시원해.",
  "mdesc_104": "스페인식 오믈렛. 감자와 양파를 넣어 요리한 것이 기본이고 새우나 하몽 등 지방 특산품을 넣은 다양한 지방의 토르티야가 있다.",
  "mdesc_105": "스페인의 쌀요리로 발렌시아 지방에서 먹던 향토 음식이다. 사프란을 넣어 밥알이 노랗게 물들어 있으며 닭고기나 토끼고기 등을 넣어 볶은 밥이다.",
  "mdesc_111": "일반 버거가 버거운 분들을 위한 작은 사이즈의 버거. \n하지만, 다른 버거가게의 일반 버거와 비슷한 크기는 안비밀.",
  "mdesc_112": "그릴에 직접 구운 패티위에 살짝 녹은 치즈맛이 일품. 작지만 알찬 버거",
  "mdesc_113": "통새우 속살을 제대로 살린 패티와 아삭한 야채와 잘 익은 토마토가 잘 어울리는 버거",
  "mdesc_114": "바삭한 튀김옷을 입은 두툼한 닭 가슴살 패티가 \n살짝 매운 맛을 머금어 자꾸만 생각나는 \n푸짐하고 맛있는 버거",
  "mdesc_115": "누가 이 버거를 정크푸드라 말할 수 있는가? 직화로 구운 두툼한 스테이크 패티가 무려 두장! 그 사이를 이어주는 치즈의 풍미가 환상적인 고품격 버거",
  "limitedpackage1": "앨리스 카드덱\n모든 메뉴 10% 할인",
  "limitedpackage2": "오즈의 마법사 카드덱\n모든 메뉴 10% 할인",
  "deckcollectbonus": "카드덱 수집 보너스 +",
  "plusbonus": " +",
  "primiumpackage": "프리미엄 카드덱",
  "votestar": "별점 남기기",
  "fanpage": "팬 페이지",
  "dmstarrestaurant": "레스토랑에서 별 {0}회 획득",
  "dm3cardplay": "[설정-세 장씩]모드로 {0}회 플레이",
  "dm1cardplay": "[설정-한 장씩]모드로 {0}회 플레이",
  "dmcardchange": "{0}종류의 카드로 플레이 ",
  "dmtouchguest": "손님 {0}회 터치 해보기",
  "dmvisitshop": "상점 {0}회 방문 하기",
  "dmvisitmoregame": "더 많은 게임 {0}회 방문 하기",
  "dmvisitfanpage": "팬 페이지 {0}회 방문 하기",
  "pandacard": "[팬더가구르면지구가돈다]를 설치하시면,\n카드를 받을 수 있습니다.\n\n다운받으러 가시겠어요?",
  "towerstar": "레스토랑에서 별 {0}개를 모았습니다. \n지금 획득하시겠습니까? ",
  "savegamedata": "게임 데이터 {0}회 저장",
  "allbonus": "덱 구매시 나의 모든 카드에 동일한 보너스 적용",
  "deckbenefit": "카드덱 혜택",
  "bonuscoin": "보너스 코인",
  "bonusstar": "보너스 별",
  "collection": "카드수집 (",
  "menudiscount": "메뉴 가격 할인",
  "owneffect": "보유 효과",
  "purchaseeffect": "구매 효과",
  "table": "테이블",
  "tablecolor": "테이블 색깔을 교체해 보세요!",
  "tablepurchase": "{0}별을 사용하여\n[{1}]테이블을\n구매 하시겠습니까?",
  "ageof2048": "[Ageof2048]을 설치하시면,\n카드를 받을 수 있습니다.\n\n다운받으러 가시겠어요?",
  "unlockcondition": "언락조건",
  "cardowncount": "보유카드 {0}개",
  "storeowncount": "보유 레스토랑 {0}개",
  "luckybonus": "행운의 카드 보너스 +",
  "luckycards": "Lucky Cards",
  "luckytoday": "오늘의 행운카드는 어떤 카드 일까요?",
  "luckyinfo": "1시간 동안 행운의 카드로 게임을 하면\n추가 보너스를 드려요!",
  "luckyretry": "별 {0}을 소모하여 \n한번 더 도전하시겠습니까?",
  "luckyeffect": "행운의 효과",
  "freespin": "Free Spin",
  "auto_disabled": "자동저장 OFF",
  "auto_datasync": "자동저장 ON",
  "auto_account_disable": "연동된 계정의 정보 변경으로 \n자동저장 기능이 해제 되었습니다.",
  "auto_account_link": "자동저장 기능을 사용을 하기 위해서는\n계정에 로그인을 해야 합니다.\n",
  "auto_sync_used": "자동저장 기능을 켜시겠습니까?\n\n통신환경에 따라 데이터가 \n소모될 수 있습니다.",
  "limitedpackage3": "오즈의 마법사 카드덱 패키지",
  "limited03purchase": "오즈의 마법사 카드덱 패키지\n구매가 완료 되었습니다.",
  "limited03restore": "오즈의 마법사 카드덱 패키지\n복원이 완료 되었습니다.",
  "auto_sync_first": "먼저 서버 데이터를\n기기에 내려받으세요. ",
  "table1": "기본",
  "table2": "초록",
  "table3": "연두",
  "table4": "보라",
  "table5": "빨강",
  "table6": "노랑",
  "table7": "앨리스",
  "table8": "아쿠아마린",
  "table9": "청록",
  "table10": "로즈 핑크",
  "table11": "미모사",
  "table12": "로즈 화이트",
  "table13": "세레니티",
  "table14": "오즈의 마법사",
  "card_name1": "기본",
  "card_name2": "에이지오브솔리테어",
  "card_name3": "쿠키",
  "card_name4": "강아지",
  "card_name5": "컵케이크",
  "card_name6": "고양이",
  "card_name7": "꽃",
  "card_name8": "클래식",
  "card_name9": "심플",
  "card_name10": "빅넘버",
  "card_name11": "레트로",
  "card_name12": "앨리스",
  "card_name13": "플라밍고",
  "card_name14": "블랙라벨",
  "card_name15": "레서판다",
  "card_name16": "과일",
  "card_name17": "하프물범",
  "card_name18": "나뭇잎",
  "card_name19": "파스텔",
  "card_name20": "유니콘",
  "card_name21": "우주",
  "card_name22": "해골",
  "card_name23": "Ageof2048",
  "card_name24": "오래된 종이",
  "card_name25": "오즈의 마법사",
  "card_name26": "바캉스",
  "card_desc1": "기본에 충실하면 누구나 성공할 수 있다.",
  "card_desc2": "솔리테어를 즐기면서 도시를 건설하세요.",
  "card_desc3": "진저쿠키는 머리부터 씹어먹어야\n맛있더라.",
  "card_desc4": "나보다 더 나를 사랑하는 유일한 친구.",
  "card_desc5": "케이크는 살 안쪄요. 당신이 쪄요.",
  "card_desc6": "고양이에 쓰는 시간은 시간낭비가 아니다",
  "card_desc7": "말로는 먹지도 못하는 꽃이라 하지만,\n선물 받으면 기분 좋더라.",
  "card_desc8": "게임을 하는 방법을 아는 것과\n이기는 방법을 아는 것을 혼돈하지 말라.",
  "card_desc9": "고민을 많이할 수록 심플함이 나오더라. ",
  "card_desc10": "큰 글씨가 반가운게 왠지 서글프다.",
  "card_desc11": "오락실에서 엄마에게 등짝 맞던\n기억이 떠오른다.",
  "card_desc12": "우린 모두 미쳤어.",
  "card_desc13": "미국에는 살아있는 플라밍고 보다 플라스틱 플라밍고가 더 많다. ",
  "card_desc14": "고득점을 노리는 당신은 이미 고급져.",
  "card_desc15": "※ 주의: 심장에 좋지 않음.",
  "card_desc16": "상큼한 과일을 즐기는 당신은 피부미인",
  "card_desc17": "덥다고 에어컨 너무 켜면 하프물범이 살기 힘들어져요!",
  "card_desc18": "떨어진 나뭇잎이 다시 그 나무의 뿌리를 이룬다.",
  "card_desc19": "파스텔은 손으로 문질러야 더 예쁘다.",
  "card_desc20": "당신은 유니콘을 본 적 있나요?",
  "card_desc21": "나는 우주에 흔적을 남기고 싶다.",
  "card_desc22": "죽는 건 순서가 없다.",
  "card_desc23": "퍼즐을 즐기면서,\n고대 이집트 문명을 건설하세요.",
  "card_desc24": "오래된 종이 냄새는 왠지 기분이 좋아요.",
  "card_desc25": "노란길을 따라가면 오즈를 만날 수 있을꺼야.",
  "card_desc26": "와우! 여름이다!",
  "guesttalk1": "네?",
  "guesttalk2": "불렀어요?",
  "guesttalk3": "무슨 일이죠?",
  "guesttalk4": "왜요?",
  "guesttalk5": "저요?",
  "guesttalk6": "저말인가요?",
  "guesttalk7": "어머?",
  "guesttalk8": "깜짝이야",
  "guesttalk9": "바빠요",
  "guesttalk10": "관심 없어요.",
  "guesttalk11": "배고파~",
  "guesttalk12": "아~ 좋은 냄새",
  "guesttalk13": "맛있는 냄새!",
  "guesttalk14": "킁킁~ 냄새 죽인다.",
  "guesttalk15": "여기가 그 유명한\n식당인가?",
  "guesttalk16": "와아~ 인테리어 좋아!",
  "guesttalk17": "여기 쉐프가 그렇게\n유명하다며?",
  "guesttalk18": "흐음~ 분위기 좋은데?",
  "guesttalk19": "여기가 SNS에서\n난리난 식당이라고?",
  "guesttalk20": "30분 대기했어",
  "guesttalk21": "제일 맛있는 거 주세요!",
  "guesttalk22": "아... 결정을 못하겠어...",
  "guesttalk23": "제가 항상 먹던 \n그거 주세요.",
  "guesttalk24": "오늘의 메뉴는 뭔가요?",
  "guesttalk25": "3인분 같은 1인분요.",
  "guesttalk26": "포장 되나요?",
  "guesttalk27": "오늘은 질보다 양으로",
  "guesttalk28": "제일 빨리 되는게 뭐죠?",
  "guesttalk29": "빨리 주세요. \n현기증 나요.",
  "guesttalk30": "제일 싱싱한 놈으로...",
  "guesttalk31": "코스요리는 없나요?",
  "guesttalk32": "후식은 역시\n소프트 아이스크림!",
  "guesttalk33": "아~ 너무 맛있었다.",
  "guesttalk34": "윽... 너무 많이 \n먹었나봐.",
  "guesttalk35": "여기 안 유명해졌음 좋겠어.",
  "guesttalk36": "다음에 또 올게요~",
  "guesttalk37": "잘 먹었습니다!",
  "guesttalk38": "다음엔 애인과 \n오고 싶다. 생기겠지?",
  "guesttalk39": "음식값이 아깝지 않아!",
  "guesttalk40": "끄윽~ \n남으면 싸가려고 했는데...",
  "guesttalk41": "여기.. 잘 될 것 같아.",
  "guesttalk42": "SNS에 올려야지! \n맛집 인증!",
  "guesttalk43": "푸드스타그램의 스타가 될꺼야!",
  "guesttalk44": "흑... 먹방 찍은 듯...",
  "guesttalk45": "야무지게 잘 먹었다.",
  "guesttalk46": "강아지도 올 수 있는\n착한 식당이야!!",
  "guesttalk47": "오늘 첫 식사에요.",
  "guesttalk48": "전 혼자 먹는 걸\n좋아해요.",
  "guesttalk49": "전 항상 식후엔\n아이스크림을 먹어요.",
  "guesttalk50": "자꾸 부르지 마세요.",
  "guesttalk51": "전 싱겁게 먹는\n스타일이에요.",
  "guesttalk52": "아보카도 너무\n맛있지 않아요?",
  "guesttalk53": "후식배는 따로 있죠.",
  "guesttalk54": "맛있는 음식은\n삶의 이유죠.",
  "guesttalk55": "짜게 먹으면\n건강에 안좋아요.",
  "guesttalk56": "식후엔 양치질.\n알고 있죠?",
  "guest_1": "미누",
  "guest_2": "아인",
  "guest_3": "호",
  "guest_4": "군",
  "guest_5": "태인",
  "guest_6": "찌",
  "guest_7": "설",
  "guest_8": "궁녀",
  "guest_9": "제임스",
  "guest_10": "카를로스",
  "guest_11": "웬디",
  "guest_1001": "칼",
  "guest_1002": "지미",
  "guest_1003": "브라이언",
  "guest_1004": "곰알바",
  "guest_101": "로스",
  "guest_102": "마이클",
  "guest_103": "제임스",
  "guest_104": "알버트",
  "guest_105": "레이첼",
  "guest_106": "모니카",
  "guest_107": "조",
  "guest_108": "에이브라함",
  "guest_109": "매기",
  "guest_110": "호세",
  "guest_111": "스티브",
  "guest_112": "유리",
  "guest_113": "샤록",
  "guest_114": "챈들러",
  "guest_115": "캐롤",
  "guest_116": "앨리스",
  "guest_117": "흰토끼",
  "guest_118": "여왕",
  "guest_119": "행운 고양이",
  "guest_120": "마스터세프",
  "guest_121": "샐럽",
  "guest_122": "제이슨",
  "guest_123": "쿠키군",
  "guest_124": "개졸려",
  "guest_125": "초콜릿",
  "guest_126": "꽃미남",
  "guest_127": "아서",
  "guest_128": "뼈다구",
  "guest_129": "슈락",
  "guest_130": "잉크",
  "guest_131": "모범생",
  "guest_132": "허세",
  "guest_133": "스파르타",
  "guest_134": "피고니스트",
  "guest_135": "넘버스",
  "guest_136": "도날드",
  "guest_137": "인민",
  "guest_138": "형님",
  "guest_139": "닥터 스트레인저",
  "guest_140": "레이디 보스",
  "guest_141": "밀러",
  "guest_142": "진",
  "guest_143": "신데렐라",
  "guest_144": "모",
  "guest_145": "프로도",
  "guest_146": "핑크",
  "guest_147": "제프",
  "guest_148": "버즈",
  "guest_149": "피카수",
  "guest_150": "클레오",
  "guest_151": "차차",
  "guest_152": "수세미밥",
  "guest_153": "도로시",
  "guest_154": "라이언",
  "guest_155": "스틸하트",
  "guest_156": "노브레인",
  "guest_157": "필립",
  "guest_158": "핑크 팡",
  "guest_159": "마린",
  "gdesc_1": "실패는 두렵지 않아요. \n맛없는 핫도그가 두려울 뿐.",
  "gdesc_2": "멕시코 요리를 너무 좋아해서 \n타코집까지 열었어요.",
  "gdesc_3": "뭐든 곱배기로 먹어야 먹은 것 같아요. \n선보이고 싶은 요리가 정말 많은데,\n이것 밖에 드릴 수 없어서 아쉽네요.",
  "gdesc_4": "맛있는 초밥의 비결은?! \n밥이 맛있어야 합니다.",
  "gdesc_5": "화덕에서 굽지 않은 피자는 \n그냥 피자맛 빵이에요.",
  "gdesc_6": "빵이나 케이크를 좋아하는 사람들은 \n다 착하고 선한 사람 같아요. ",
  "gdesc_7": "매운 음식은 머리 꼭대기에서 땀이 \n뿜어져 나와야 정답이지.",
  "gdesc_8": "나는 절대미각의 소유자. 음, 이 요리는 \n닭육수에 계란, 토마토, 바퀴벌레... 우엑!!!! ",
  "gdesc_9": "딤섬은 한입에 먹어야 육즙이 터지는 것을 제대로 느낄 수 있지. 앗 뜨거!!! ",
  "gdesc_10": "사랑과 정열의 요리를 맛보여 주겠어!",
  "gdesc_11": "제대로만 만들면 햄버거야 말로 완전식품 이라구!",
  "gdesc_1001": "식당 인테리어 공사는 내가 전문가지!",
  "gdesc_1002": "내가 추구하는 인테리어는 이쁜게 아니라 \n음식이 맛있어 보이는 거야. ",
  "gdesc_1003": "최고의 쿠킹타워를 지을꺼야. ",
  "gdesc_1004": "날 만나면 행운이 와요!",
  "gdesc_101": "음식을 남기는 건 죄야.",
  "gdesc_102": "먹고 돌아서면 배고파. ",
  "gdesc_103": "오늘 데이트는 어디서 할까? \n겹치면 안되는데.",
  "gdesc_104": "그녀를 위해 최고의 레스토랑을 찾을꺼야.",
  "gdesc_105": "뭔가 상큼한게 먹고 싶어. 뭐가 있을까?",
  "gdesc_106": "난 우울해지면 케이크를 찾아. \n부드러운 맛이 날 위로해주거든. ",
  "gdesc_107": "여기에서 이렇게 맛있는 스시를 \n맛볼 줄은 몰랐어.",
  "gdesc_108": "이 타워에 그냥 살고 싶다. ",
  "gdesc_109": "어떤 식당이 또 생길까? 아 너무 궁금해!",
  "gdesc_110": "맛집을 찾아 다니는 여행만큼 \n행복한 여행은 없어.",
  "gdesc_111": "여기에 오면 고향의 음식을 먹을 수 있어 \n너무 좋아.",
  "gdesc_112": "다이어트는 원래 내일부터. ",
  "gdesc_113": "똑같은 레시피로 만드는데, 이 집이 \n더 맛있는 이유를 밝혀내고야 말겠어.",
  "gdesc_114": "와우! 친구들에게 \n여기 꼭 소개시켜줘야겠어.",
  "gdesc_115": "내 까다로운 입맛을 만족시키는 \n식당은 찾기 힘들지.",
  "gdesc_116": "내 기분은 내가 정해. \n오늘 나는 '행복'으로 할래",
  "gdesc_117": "아이고! 늦었다! 늦었어!",
  "gdesc_118": "저것의 목을 쳐라",
  "gdesc_119": "나는 복을 주는 고양이다냥.\n너! 나를 키워라!",
  "gdesc_120": "이렇게 욕나오게 멋진 레스토랑을 \n본적이 없어!",
  "gdesc_121": "팔로 팔로 팔로 미~",
  "gdesc_122": "내가 궁금해?",
  "gdesc_123": "머리부터 먹어야 맛있지!",
  "gdesc_124": "자도 자도 계속 졸려.",
  "gdesc_125": "외롭고 슬플땐 케이크 앞으로",
  "gdesc_126": "꽃을 볼 때마다 네가 생각나.",
  "gdesc_127": "검 뽑는 것보다 이 게임이 더 재밌어.",
  "gdesc_128": "요즘 근육이 붙는 것 같아.",
  "gdesc_129": "눈이 안좋은건 내 탓이 아니라구..",
  "gdesc_130": "왜 날 자꾸 젤다라 부르는 거야?",
  "gdesc_131": "매일매일 출석했어요.",
  "gdesc_132": "난 한번 입은 속옷은 안입거든?",
  "gdesc_133": "다이어트라...\n내가 유일하게 잘 못하는 것이지.",
  "gdesc_134": "이 게임이 날 못자게 해.",
  "gdesc_135": "모든 맛은 숫자로 표현할 수 있어. \n이 맛은... 무한대야!",
  "gdesc_136": "이 건물 맘에 듭니다! 얼마에요? \n부르는 값에 무조껀 10배!! 딜?!",
  "gdesc_137": "3카드가 좀 어렵지만, \n아 어렵다고 말하면 안 되갔구나.",
  "gdesc_138": "이 게임 일본번역 내가 했거등?! \n나 장가갈 수 있게 도와줘!",
  "gdesc_139": "시간을 돌려서 동영상을 본것처럼!",
  "gdesc_140": "음식에 손대지마! 아직 사진 안찍었어.",
  "gdesc_141": "게임 데이터 저장하기는 정말 중요합니다.",
  "gdesc_142": "천일동안 주인님을 기다렸어요.",
  "gdesc_143": "애도 아니고 어떻게 놀다가 매번 \n그 시간에 들어가요?",
  "gdesc_144": "더울때는 얼음과 수박을 갈아서 만든 \n땡모반이 최고지!",
  "gdesc_145": "저 마지막 잎새가 떨어지기 전에 \n애인이 생겼으면…",
  "gdesc_146": "뭔가 상큼하고 보기에 예쁜 음식을 \n먹고 싶어.",
  "gdesc_147": "내가 실리콘벨리에서 엄청 잘나가거든!",
  "gdesc_148": "무한한 공간 저 너머로!",
  "gdesc_149": "좋은 예술가는 베끼고, \n위대한 예술가는 훔친다.",
  "gdesc_150": "Just One 10 MINUTES \n내 것이 되는 시간",
  "gdesc_151": "오늘은 정열적인 빨강이 끌려.",
  "gdesc_152": "태어날 때 부터 노랑머리는 아니였어요.",
  "gdesc_153": "나는 더이상 켄자스에 있지 않아. ",
  "gdesc_154": "살살 얘기해. 무서웡.",
  "gdesc_155": "나도 다시 사랑하고 싶어.",
  "gdesc_156": "사람들도 생각없이 많은 말을 하지 않니?",
  "gdesc_157": "이번 휴가를 위해 1년을 저축했어!",
  "gdesc_158": "핑크는 사랑을 부르는 색이야. ",
  "gdesc_159": "더울 땐 시원한 색을 골라봐. ",
  "stroe_retime0": "0{0} day",
  "achievement_1": "55연승",
  "achievement_2": "111연승",
  "achievement_3": "333연승",
  "achievement_4": "555연승",
  "achievement_5": "777연승",
  "achievement_6": "200판 하기",
  "achievement_7": "500판 하기",
  "achievement_8": "1000판 하기",
  "achievement_9": "3000판 하기",
  "achievement_10": "10000판 하기",
  "achievement_11": "3일 연속 게임",
  "achievement_12": "5일 연속 게임",
  "achievement_13": "7일 연속 게임",
  "achievement_14": "14일 연속 게임",
  "achievement_15": "30일 연속 게임",
  "achievement_16": "동영상 광고 시청 5번",
  "achievement_17": "동영상 광고 시청 10번",
  "achievement_18": "동영상 광고 시청 20번",
  "achievement_19": "동영상 광고 시청 50번",
  "achievement_20": "동영상 광고 시청 100번",
  "achievement_21": "모닝게임 3회",
  "achievement_22": "모닝게임 10회",
  "achievement_23": "모닝게임 20회",
  "achievement_24": "모닝게임 50회",
  "achievement_25": "모닝게임 100회",
  "achievement_26": "새벽게임 3회",
  "achievement_27": "새벽게임 10회",
  "achievement_28": "새벽게임 20회",
  "achievement_29": "새벽게임 50회",
  "achievement_30": "새벽게임 100회",
  "achievement_31": "카드덱 1개 모으기",
  "achievement_32": "카드덱 2개 모으기",
  "achievement_33": "카드덱 3개 모으기",
  "achievement_34": "카드덱 4개 모으기",
  "achievement_35": "카드덱 5개 모으기",
  "achievement_36": "플레이시간 100분",
  "achievement_37": "플레이시간 300분",
  "achievement_38": "플레이시간 500분",
  "achievement_39": "플레이시간 1000분",
  "achievement_40": "플레이시간 5000분",
  "achievement_41": "셔플아이템 10회 사용",
  "achievement_42": "셔플아이템 50회 사용",
  "achievement_43": "셔플아이템 100회 사용",
  "achievement_44": "셔플아이템 300회 사용",
  "achievement_45": "셔플아이템 500회 사용",
  "achievement_46": "힌트아이템 10회 사용",
  "achievement_47": "힌트아이템 50회 사용",
  "achievement_48": "힌트아이템 100회 사용",
  "achievement_49": "힌트아이템 300회 사용",
  "achievement_50": "힌트아이템 500회 사용",
  "achievement_51": "되돌리기아이템 10회 사용",
  "achievement_52": "되돌리기아이템 50회 사용",
  "achievement_53": "되돌리기아이템 100회 사용",
  "achievement_54": "되돌리기아이템 300회 사용",
  "achievement_55": "되돌리기아이템 500회 사용",
  "achievement_56": "쿠키카드덱 10회 사용",
  "achievement_57": "쿠키카드덱 50회 사용",
  "achievement_58": "쿠키카드덱 100회 사용",
  "achievement_59": "쿠키카드덱 300회 사용",
  "achievement_60": "쿠키카드덱 500회 사용",
  "achievement_61": "강아지카드덱 10회 사용",
  "achievement_62": "강아지카드덱 50회 사용",
  "achievement_63": "강아지카드덱 100회 사용",
  "achievement_64": "강아지카드덱 300회 사용",
  "achievement_65": "강아지카드덱 500회 사용",
  "achievement_66": "컵케이크카드덱 10회 사용",
  "achievement_67": "컵케이크카드덱 50회 사용",
  "achievement_68": "컵케이크카드덱 100회 사용",
  "achievement_69": "컵케이크카드덱 300회 사용",
  "achievement_70": "컵케이크카드덱 500회 사용",
  "achievement_71": "고양이카드덱 10회 사용",
  "achievement_72": "고양이카드덱 50회 사용",
  "achievement_73": "고양이카드덱 100회 사용",
  "achievement_74": "고양이카드덱 300회 사용",
  "achievement_75": "고양이카드덱 500회 사용",
  "achievement_76": "꽃카드덱 10회 사용",
  "achievement_77": "꽃카드덱 50회 사용",
  "achievement_78": "꽃카드덱 100회 사용",
  "achievement_79": "꽃카드덱 300회 사용",
  "achievement_80": "꽃카드덱 500회 사용",
  "achievement_81": "클래식카드덱 10회 사용",
  "achievement_82": "클래식카드덱 50회 사용",
  "achievement_83": "클래식카드덱 100회 사용",
  "achievement_84": "클래식카드덱 300회 사용",
  "achievement_85": "클래식카드덱 500회 사용",
  "achievement_86": "심플카드덱 10회 사용",
  "achievement_87": "심플카드덱 50회 사용",
  "achievement_88": "심플카드덱 100회 사용",
  "achievement_89": "심플카드덱 300회 사용",
  "achievement_90": "심플카드덱 500회 사용",
  "achievement_91": "게임 데이터 저장하기",
  "achievement_92": "빅넘버 카드덱 30회  사용",
  "achievement_93": "빅넘버 카드덱 50회  사용",
  "achievement_94": "빅넘버 카드덱 100회  사용",
  "achievement_95": "레트로 카드덱 30회 사용  ",
  "achievement_96": "레트로 카드덱 50회 사용",
  "achievement_97": "레트로 카드덱 100회 사용",
  "achievement_98": "플라밍고 카드덱 30회 사용 ",
  "achievement_99": "플라밍고 카드덱 50회 사용 ",
  "achievement_100": "플라밍고 카드덱 100회 사용",
  "achievement_101": "블랙라벨 카드덱 30회 사용",
  "achievement_102": "블랙라벨 카드덱 50회 사용",
  "achievement_103": "블랙라벨 카드덱 100회 사용",
  "achievement_104": "하프물범 카드덱 30회 사용",
  "achievement_105": "하프물범 카드덱 50회 사용",
  "achievement_106": "하프물범 카드덱 100회 사용",
  "achievement_107": "나뭇잎 카드덱 30회 사용",
  "achievement_108": "나뭇잎 카드덱 50회 사용",
  "achievement_109": "나뭇잎 카드덱 100회 사용",
  "achievement_110": "파스텔 카드덱 30회 사용",
  "achievement_111": "파스텔 카드덱 50회 사용",
  "achievement_112": "파스텔 카드덱 100회 사용",
  "achievement_113": "유니콘 카드덱 30회 사용",
  "achievement_114": "유니콘 카드덱 50회 사용",
  "achievement_115": "유니콘 카드덱 100회 사용",
  "achievement_116": "우주 카드덱 30회 사용",
  "achievement_117": "우주 카드덱 50회 사용",
  "achievement_118": "우주 카드덱 100회 사용",
  "achievement_119": "해골 카드덱 30회 사용",
  "achievement_120": "해골 카드덱 50회 사용",
  "achievement_121": "해골 카드덱 100회 사용",
  "achievement_122": "오래된 종이 카드덱 30회 사용",
  "achievement_123": "오래된 종이 카드덱 50회 사용",
  "achievement_124": "오래된 종이 카드덱 100회 사용",
  "tutorial0": "셰프님~ 어서오세요.\n[솔리테어 쿠킹타워]에 오신 것을\n환영합니다.",
  "tutorial1": "자 먼저 제일 중요한 솔리테어 \n게임 방법을 알려드릴께요. :)",
  "tutorial2": "아래 부분이 카드를 이동하며\n게임을 진행하는 <font color=0xFF0000>타블로</font> 입니다.",
  "tutorial3": "카드는 K카드부터 에이스 카드까지\n차례로 쌓을 수 있습니다.",
  "tutorial4": "<font color=0xFF0000>빨간색</font>과 <font color=0x000000>검은색</font> 카드를 교차하여 \n번갈아 쌓을 수 있으며,\n빈 줄에는 K만 이동할 수 있습니다.",
  "tutorial5": "자, <font color=0xFF0000>Q♥</font> 카드를 탭하여 <font color=0x000000>\nK♠</font> 카드 밑으로 이동하세요.",
  "tutorial6": "잘했어요! 다음엔<font color=0x000000> J♣</font> 카드를 탭하여<font color=0xFF0000>\nQ♥</font> 카드 밑으로 이동하세요.",
  "tutorial7": "네! 좋아요. 다음엔...? 그렇죠!<font color=0xFF0000> 10◆</font>\n카드를 움직일 차례죠?",
  "tutorial8": "카드를 이동할 때, 연결된 카드들은 \n묶음으로 움직일 수 있습니다.\n<font color=0x000000> K♠ </font> 카드를 눌러보세요. \n빈칸으로 이동합니다.\n빈칸에는 K카드만 이동할 수 있습니다.",
  "tutorial9": "상단에 빈 곳은 <font color=0xFF0000>파운데이션</font>입니다.\n에이스부터 K까지 순차적으로\n<font color=0xFF0000>파운데이션</font>에 4벌의 \n카드를 모두 쌓으면 게임을 \n클리어 하게 됩니다.",
  "tutorial10": "<font color=0xFF0000>A◆</font> 카드를 탭하여<font color=0xFF0000> 파운데이션 </font>으로 이동시키세요.",
  "tutorial11": "셰프님, 잘하셨습니다. \n앗, 지금<font color=0xFF0000> 콤보카드 </font>가 생성되었어요!",
  "tutorial12": "콤보카드는<font color=0x0000FF> 연속으로 5번 </font>점수를 \n획득하면 발생합니다. 콤보카드를 일정 시간 내에<font color=0xFF0000> 파운데이션</font>으로 이동하면 \n별을 얻을 수 있어요.",
  "tutorial13": "<font color=0x000000>A♣</font> 카드를 탭하여<font color=0xFF0000> 파운데이션</font> 으로 이동하세요.",
  "tutorial14": "와우! 별을 획득했어요!\n별은<font color=0xFF0000> 카드덱 상점</font>에서<font color=0xFF0000> 카드덱</font>을 \n구매할 때 사용합니다.",
  "tutorial15": "어라? 셰프님! \n이젠 이동할 카드가 없어요. \n이럴 때에는<font color=0xFF0000> 웨이스트 </font>에 있는 카드를\n뒤집어서 사용할 수 있어요. ",
  "tutorial16": "<font color=0xFF0000>웨이스트</font>카드를 탭하세요.",
  "tutorial17": "<font color=0xFF0000>웨이스트</font>에 있는 카드는<font color=0xFF0000> 타블로</font>나\n<font color=0xFF0000>파운데이션</font>으로 바로 이동이 가능합니다. <font color=0x000000>9♠</font>를 탭하세요.",
  "tutorial18": "자, 셰프님. 이것으로 기본적인\n게임 방법 설명을 마쳤습니다!\n감사의 선물로 아이템을 드렸어요!\n그럼 이제 즐거운 쿠킹 타워로 출발! ",
  "share": "공유",
  "timeline_success": "타임라인에 글을 게시하였습니다.",
  "message_send": "친구에게 메세지를 보내시겠습니까?",
  "message_success": "메시지를 보냈습니다.",
  "version_check": "버전이 일치하지 않습니다. 앱 종료 후 재 실행하여 주세요.",
  "nomoreshuffle": "패섞기를 사용할 수 없는 상태입니다.",
  "timeline_send": "타임라인에 글을 게시하시겠습니까?",
  "double_coin": "코인 2배 획득!",
  "nomoreundo": "되돌리기를 사용할 수 없는 상태입니다.",
  "preventguide": "본 게임은 세로로만 플레이하실 수 있습니다.",
  "tower_share": "이것이 내 쿠킹타워다! 다들 내 쿠킹타워를 봐 줘!",
  "current_invite": "현재 초대 인원",
  "people": "명",
  "invite_fix": "같은 친구 초대 시 인원 수는 증가하지 않습니다.",
  "invite_getcard": "40명 초대시 레서판다카드 지급",
  "share_message": "{0}님과 함께 {1}을 즐겨보세요!",
  "share_invite": "게임하러 가기",
  "menu_invite_message": "친구에게 자랑하고 별 15개를 추가로 받으세요!",
  "store_share_message": "타임라인에 공유하면 별 30개를 받을 수 있어요.",
  "watch_ad": "광고 보기",
  "triple_coin": "모두 수행 시, 코인 3배 획득!",
  "friendPos_message": "{0}층 진행 중…",
  "tuto_skip": "스킵 하시겠습니까?"
}